humor/__init__.py
humor/humor.py
humor-0.0.0.dist-info/LICENSE
humor-0.0.0.dist-info/METADATA
humor-0.0.0.dist-info/WHEEL
humor-0.0.0.dist-info/top_level.txt
humor-0.0.0.dist-info/RECORD
